[
  {
    "id": "SyAZl55NU",
    "name": "Du evssel"
  },
  {
    "id": "BJ8Kxc5EL",
    "name": "Du evssel",
    "type": "wewewe"
  },
  {
    "id": "HysEv5cNL",
    "name": "Du evssel",
    "type": "wewewedsdsdds"
  },
  {
    "id": "SygO_554U"
  },
  {
    "id": "HJvjuqcNI"
  },
  {
    "id": "HkoJFq9E8"
  },
  {
    "id": "ByGnt55VI",
    "name": "Du evs434343dsdsel",
    "type": "5dsdsdsd555"
  },
  {
    "id": "HyI2yi5EL",
    "name": "Du esdsel",
    "type": "5dsdsdsd555"
  },
  {
    "id": "rkgygi54I",
    "name": "Du es",
    "type": "5dsdsdsd555"
  }
]